mqt/qusat/py.typed
mqt/qusat/pyqusat.cp314-win_arm64.pyd
mqt/qusat/pyqusat.pyi
mqt/qusat/_version.py
mqt/qusat/_version.pyi
mqt/qusat/__init__.py
mqt_qusat-1.4.0.dist-info/DELVEWHEEL
mqt_qusat-1.4.0.dist-info/METADATA
mqt_qusat-1.4.0.dist-info/RECORD
mqt_qusat-1.4.0.dist-info/WHEEL
mqt_qusat-1.4.0.dist-info/licenses/LICENSE.md
mqt_qusat.libs/libz3-f1940966ac2a0959c0c51062d8465ee8.dll
mqt_qusat.libs/msvcp140-161a5565c271985a71fb801bf554f2ff.dll
