Metadata-Version: 2.4
Name: mqt.qusat
Version: 1.4.0
Summary: MQT QuSAT - A Tool for Utilizing SAT in Quantum Computing
Keywords: MQT,quantum-computing,design-automation,satisfiability
Author-Email: Lucas Berent <lucas.berent@tum.de>, Lukas Burgholzer <lukas.burgholzer@tum.de>
License-Expression: MIT
License-File: LICENSE.md
Classifier: Development Status :: 5 - Production/Stable
Classifier: Programming Language :: Python :: 3
Classifier: Programming Language :: Python :: 3 :: Only
Classifier: Programming Language :: Python :: 3.10
Classifier: Programming Language :: Python :: 3.11
Classifier: Programming Language :: Python :: 3.12
Classifier: Programming Language :: Python :: 3.13
Classifier: Programming Language :: C++
Classifier: Operating System :: Microsoft :: Windows
Classifier: Operating System :: MacOS
Classifier: Operating System :: POSIX :: Linux
Classifier: Intended Audience :: Science/Research
Classifier: Natural Language :: English
Classifier: Topic :: Scientific/Engineering :: Electronic Design Automation (EDA)
Classifier: Typing :: Typed
Project-URL: Homepage, https://github.com/munich-quantum-toolkit/qusat
Project-URL: Issues, https://github.com/munich-quantum-toolkit/qusat/issues
Project-URL: Discussions, https://github.com/munich-quantum-toolkit/qusat/discussions
Project-URL: Research, https://www.cda.cit.tum.de/research/quantum
Requires-Python: >=3.10
Requires-Dist: mqt.core~=3.3.1
Provides-Extra: qiskit
Requires-Dist: qiskit[qasm3-import]>=1.0.0; extra == "qiskit"
